<?xml version='1.0' encoding='utf-8' standalone='yes' ?>
<map>
    <int name="quoted_text_picker" value="-463143" />
    <boolean name="disable_hiddenchat_access" value="false" />
    <boolean name="my_statusd" value="false" />
    <boolean name="imsHideVStatus" value="false" />
    <int name="scdleft" value="2" />
    <boolean name="bYW_Waa_DA_home" value="false" />
    <int name="key_updown_iconcolor" value="-1305" />
    <boolean name="date_bubble_color_picker_Gactive" value="false" />
    <boolean name="Conv_call_btn" value="false" />
    <boolean name="ModFabTextColor_Gactive" value="false" />
    <int name="key_mas_border_avatar_quick_contact" value="-36530" />
    <int name="key_msnewstab_tl_Cst" value="50" />
    <boolean name="key_hide_unsaved_num" value="false" />
    <boolean name="HomeBarText_Gactive" value="false" />
    <int name="key_msnewstcabeH_GC" value="-1324645" />
    <boolean name="bYW_Waa_GO_home" value="false" />
    <int name="key_msnewstab_br_Cst" value="50" />
    <boolean name="MetaAI" value="false" />
    <int name="bYW_Waa_WWe_home" value="-1324645" />
    <int name="key_dwh_size_row" value="79" />
    <int name="statusleft" value="0" />
    <int name="ConvoBack" value="-12969962" />
    <boolean name="onlinechat" value="false" />
    <boolean name="key_msnewstcabeH_Gactive" value="false" />
    <boolean name="enable_fivminstatus" value="true" />
    <boolean name="key_tt" value="true" />
    <string name="convostyle">3</string>
    <int name="key_msnewstntabtela_GC" value="520093696" />
    <int name="HomeCounterBK" value="-2470337" />
    <string name="key_chats_icon">22</string>
    <int name="ModChatBubbleTextLeft" value="-463143" />
    <boolean name="enable_grp_separationV2" value="true" />
    <int name="quoted_divider_picker" value="-2470337" />
    <int name="ModFabTextColor" value="-662856" />
    <boolean name="key_counter_tx_Gactive" value="false" />
    <boolean name="ModConTextColor_Gactive" value="false" />
    <int name="mswa_LxB_hM_WXW" value="-1324645" />
    <int name="key_msnewstab_bl_C" value="50" />
    <int name="key_msnewschat" value="-12969962" />
    <int name="key_warDay" value="-16777216" />
    <int name="key_msnewstabS" value="-16777216" />
    <boolean name="key_mnt5" value="true" />
    <boolean name="yo_hideinfo" value="true" />
    <boolean name="key_mnt4" value="true" />
    <boolean name="key_mnt3" value="true" />
    <int name="key_msnewstcabe" value="-12969962" />
    <boolean name="key_botcurva" value="true" />
    <string name="ppsh">4</string>
    <boolean name="key_grt" value="true" />
    <string name="ppsf">4</string>
    <boolean name="tabadgeBKColor_Gactive" value="false" />
    <boolean name="arch_chats_top" value="true" />
    <boolean name="key_scn4" value="true" />
    <boolean name="quickBK_check" value="true" />
    <int name="key_msnewstntabconfig_GOrient" value="0" />
    <int name="key_msnewstntab2" value="35" />
    <boolean name="key_scn5" value="true" />
    <boolean name="key_scn2" value="true" />
    <int name="key_msnewstntab4" value="1" />
    <boolean name="key_scn3" value="true" />
    <boolean name="abu_saleh_research" value="false" />
    <string name="key_community_icon">14</string>
    <boolean name="onlineDotchat" value="false" />
    <int name="key_msnewbottom1" value="-2470337" />
    <int name="key_msnewbottom2" value="31" />
    <int name="ModlastseenColor" value="-16777216" />
    <int name="key_mas_setBackground_quick_GOrient" value="0" />
    <int name="key_msnewbottom3" value="1" />
    <boolean name="Hide_contact_picker_section_frequent_chats" value="false" />
    <boolean name="status_wantsendconfirmation" value="true" />
    <boolean name="key_msnewstab_custom_corners_Cc" value="false" />
    <int name="ModDarkConPickColorNav" value="-12969962" />
    <int name="key_msnewstntab1" value="-12969962" />
    <int name="key_msnewstab2" value="36" />
    <boolean name="key_headerRE" value="true" />
    <int name="quoted_bg_picker" value="-2470337" />
    <int name="ModChatGStatusB_GCDir" value="0" />
    <boolean name="statuschat" value="false" />
    <boolean name="key_msnewstab_custom_corners_Cst" value="true" />
    <int name="key_msnewstntabname" value="-2470337" />
    <boolean name="runtex" value="true" />
    <boolean name="ModDarkConPickColorNav_Gactive" value="false" />
    <int name="key_counter_bg" value="-2470337" />
    <int name="ModChatColor" value="0" />
    <boolean name="blurConfig" value="true" />
    <boolean name="hide_translation_icon" value="false" />
    <boolean name="HomeCounterBK_Gactive" value="false" />
    <boolean name="key_mstellC" value="true" />
    <boolean name="key_mstellB" value="false" />
    <boolean name="key_mnt2" value="true" />
    <int name="ModConBackColor_GC" value="-1324645" />
    <int name="key_mas_icon_quickcontact" value="-2470337" />
    <int name="key_msnewstntab" value="-12969962" />
    <int name="key_msnewstab_tl_HC" value="0" />
    <boolean name="date_right_color_Gactive" value="false" />
    <boolean name="quickText_check" value="true" />
    <int name="quickBK_GC" value="-1324645" />
    <int name="key_ms_icon" value="-2470337" />
    <int name="key_msnewstcabeH_GOrient" value="0" />
    <boolean name="key_grsHeader" value="true" />
    <string name="key_custom_iconup">10</string>
    <int name="key_msnewstab_tl_HX" value="0" />
    <boolean name="hide_fab" value="false" />
    <boolean name="ModChatGStatusT_Gactive" value="false" />
    <int name="ModConBackColor_GCDir" value="0" />
    <string name="ui_bottom_style">bywa4</string>
    <boolean name="my_name" value="true" />
    <boolean name="key_msnewstntabconfig_Gactive" value="false" />
    <int name="jmsize" value="43" />
    <int name="pagetitle_picker" value="-1324645" />
    <boolean name="TxtSelect" value="false" />
    <int name="ModChatGStatusB_GC" value="-1324645" />
    <int name="size_tab" value="60" />
    <boolean name="key_NewPer1" value="true" />
    <int name="jmleft" value="346" />
    <boolean name="key_botPP" value="false" />
    <int name="emojipopup_header_GC" value="-1324645" />
    <boolean name="hide_action_a" value="false" />
    <boolean name="hide_action_b" value="false" />
    <boolean name="key_meler1" value="true" />
    <string name="key_inicio_icon">12</string>
    <boolean name="ConvoBack_Gactive" value="false" />
    <boolean name="key_msnewstab_custom_corners_HX" value="true" />
    <int name="key_msnewstab_br_HX" value="50" />
    <int name="key_dwh_size_banner" value="180" />
    <int name="key_msnewstab_GOrient" value="0" />
    <boolean name="key_name_stories_Gactive" value="false" />
    <boolean name="quoted_text_picker_Gactive" value="false" />
    <boolean name="key_dateR2" value="true" />
    <boolean name="statuses_bar_text_picker_Gactive" value="false" />
    <int name="ConvoBack_GCDir" value="0" />
    <boolean name="key_ms_animed" value="false" />
    <int name="key_msnewsf2" value="12" />
    <int name="pagerbottom" value="85" />
    <boolean name="key_comun" value="true" />
    <int name="key_msnewstab_br_HC" value="0" />
    <boolean name="key_msnewstab_custom_corners_HC" value="true" />
    <int name="ModDarkConPickColor_GC" value="-1065528" />
    <int name="text_size_pick" value="12" />
    <int name="key_ms_bordab" value="-1324645" />
    <string name="key_chat_animation">11</string>
    <boolean name="key_updown_bgcolor_Gactive" value="false" />
    <string name="key_quick_position">top</string>
    <boolean name="quoted_bg_picker_Gactive" value="true" />
    <string name="menit3">0</string>
    <string name="menit1">0</string>
    <boolean name="hide_action_s" value="true" />
    <int name="ModFabNormalColor" value="-12969962" />
    <boolean name="key_msbot" value="true" />
    <boolean name="hide_action_l" value="true" />
    <boolean name="hide_action_m" value="false" />
    <string name="key_admicon_list">13</string>
    <int name="key_msnewstntabname2" value="5" />
    <int name="UnSeenColor" value="-2470337" />
    <int name="date_right_color" value="-463143" />
    <int name="key_msnewstabS_GC" value="-1324645" />
    <boolean name="key_msnewstab_custom_corners_S" value="false" />
    <string name="jamm">0</string>
    <boolean name="NameProf" value="false" />
    <boolean name="emojipopup_body_Gactive" value="false" />
    <boolean name="key_msnewstab_custom_corners_T" value="false" />
    <int name="mntleft" value="2" />
    <boolean name="key_mstell" value="true" />
    <int name="key_msnewscar_GOrient" value="0" />
    <int name="quickText" value="-463143" />
    <boolean name="ModChaSendBKColor_Gactive" value="false" />
    <int name="key_msnewbottom" value="-12969962" />
    <boolean name="pagetitle_sel_picker_Gactive" value="false" />
    <boolean name="key_dg1" value="true" />
    <int name="ModDarkConPickColor" value="-12969962" />
    <boolean name="key_hide_scrolldown" value="false" />
    <boolean name="key_dg2" value="true" />
    <int name="pagerright" value="17" />
    <int name="ModConTextColor" value="-662856" />
    <boolean name="key_with_thumb" value="false" />
    <boolean name="disableDTTL" value="false" />
    <int name="TextDateDrawer2" value="-16777216" />
    <int name="key_updown_bgcolor_GC" value="-36530" />
    <boolean name="key_scn" value="true" />
    <int name="key_msnewstntabconfig" value="1513756694" />
    <boolean name="key_dg5" value="true" />
    <boolean name="key_dg6" value="true" />
    <string name="jaaam2">0</string>
    <boolean name="key_dg3" value="true" />
    <boolean name="date_divider_color_picker_Gactive" value="false" />
    <boolean name="key_dg4" value="true" />
    <boolean name="key_dg7" value="true" />
    <boolean name="key_dg8" value="true" />
    <boolean name="key_msnewstab_custom_corners_CstB" value="false" />
    <boolean name="SeenColor_Gactive" value="false" />
    <boolean name="btn_voice_color_chat_picker_Gactive" value="false" />
    <int name="key_msnewstntab_GOrient" value="0" />
    <int name="key_msnewstabSB_GOrient" value="0" />
    <int name="ModChatBtnColor" value="-2470337" />
    <boolean name="key_counter_bg_Gactive" value="false" />
    <boolean name="ModChatLeftBubble_Gactive" value="false" />
    <int name="key_msnewstab_bl_Cst" value="50" />
    <boolean name="abu_saleh_key_fab_caht" value="true" />
    <boolean name="AttBt" value="false" />
    <int name="ModDarkConPickColor_GOrient" value="0" />
    <boolean name="key_frameAtas" value="true" />
    <string name="home_stories_style">view</string>
    <boolean name="ModDarkConPickColor_Gactive" value="false" />
    <boolean name="ModChatBubbleText_Gactive" value="false" />
    <int name="date_bubble_color_picker" value="-12969962" />
    <int name="seekbar_color_chat_picker" value="-463143" />
    <boolean name="key_msnewscar_Gactive" value="false" />
    <int name="ModFabPressedColor" value="-4749920" />
    <int name="statuses_bar_bg_picker" value="0" />
    <int name="ModChatGStatusB" value="-12969962" />
    <boolean name="emojipopup_icons_Gactive" value="false" />
    <int name="emojipopup_header" value="-12969962" />
    <int name="HomeBarText" value="-1324645" />
    <boolean name="imsHideRStatus" value="false" />
    <boolean name="key_headerREnew" value="true" />
    <int name="ModChatGStatusT" value="-662856" />
    <boolean name="key_hour3" value="true" />
    <boolean name="key_msnewstabS_check" value="true" />
    <boolean name="key_hour2" value="true" />
    <int name="statuses_bar_text_picker" value="-662856" />
    <boolean name="ModHomeMentionIndBackground_Gactive" value="false" />
    <boolean name="isSwipeEnabledV2" value="false" />
    <boolean name="seekbar_color_chat_picker_Gactive" value="false" />
    <int name="emojipopup_body_GCDir" value="0" />
    <int name="Dleft" value="2" />
    <boolean name="key_hour5" value="true" />
    <boolean name="key_hour4" value="true" />
    <boolean name="admin_abosaleh" value="false" />
    <string name="key_group_icon">21</string>
    <boolean name="read_more" value="false" />
    <string name="abu_saleh_quickcontact">4</string>
    <int name="key_mas_setBackground_quick" value="-12969962" />
    <boolean name="yo_want_nightmode" value="true" />
    <boolean name="key_updown_bgcolor_check" value="true" />
    <int name="quickBK" value="-12969962" />
    <boolean name="key_grsPx2" value="true" />
    <boolean name="key_msnewstntabconfig_check" value="true" />
    <int name="key_msnewstntabtela_GOrient" value="0" />
    <boolean name="ModChatBubbleTextLeft_Gactive" value="false" />
    <boolean name="ModChatEntry_Gactive" value="false" />
    <boolean name="key_dayToxE" value="true" />
    <int name="key_msnewstabS_GOrient" value="0" />
    <boolean name="ModFabNormalColor_Gactive" value="false" />
    <int name="participant_name_color_picker" value="-463143" />
    <string name="key_pager_animation">4</string>
    <boolean name="Audio_ears" value="false" />
    <int name="ModChatEntry" value="-12969962" />
    <boolean name="key_msnewstabSB_Gactive" value="false" />
    <boolean name="bYW_Waa_COR_home_Gactive" value="false" />
    <int name="square_photo_ratio_picker" value="100" />
    <boolean name="statuses_bar_bg_picker_Gactive" value="false" />
    <boolean name="bYW_Waa_WWe_home_Gactive" value="false" />
    <int name="key_msnewstntabtela" value="520093696" />
    <boolean name="key_regg" value="true" />
    <string name="key_status_ui">0</string>
    <string name="key_dial1">0</string>
    <string name="hazar_bozkurt_sesler_gidenmesaj">0</string>
    <string name="key_dial3">1</string>
    <int name="ConvoBack_GC" value="-793131" />
    <int name="key_msnewstabSB_GC" value="-1324645" />
    <boolean name="key_msnewstntab_Gactive" value="false" />
    <int name="ModConColor_GC" value="-1324645" />
    <boolean name="key_headerNA" value="true" />
    <boolean name="key_headerNB" value="true" />
    <int name="SeenColor" value="-12969962" />
    <boolean name="yo_want_toolbar_cam" value="false" />
    <int name="ModOnlineColor" value="-10658467" />
    <boolean name="abu_saleh_status_and_photo" value="true" />
    <int name="key_msnews4" value="1" />
    <int name="key_msnews1" value="-2470337" />
    <int name="ModChaSendBKColor" value="-2470337" />
    <int name="key_msnews2" value="5" />
    <string name="key_ghost_icon">16</string>
    <boolean name="ModContactNameColor_Gactive" value="false" />
    <int name="key_ms_Perff" value="-2470337" />
    <boolean name="newAttach_BottomDesign" value="false" />
    <boolean name="key_msnewstcabeH_check" value="true" />
    <boolean name="Hide_div" value="true" />
    <boolean name="key_msnewschat_check" value="true" />
    <boolean name="quickBK_Gactive" value="false" />
    <boolean name="yo_want_ghostmode" value="false" />
    <boolean name="key_mas_hide_archive_home" value="false" />
    <boolean name="key_hour" value="true" />
    <string name="jammnew">0</string>
    <boolean name="key_msnewstab_custom_corners_SF" value="false" />
    <int name="key_msnewstab_GC" value="657342532" />
    <string name="key_status_icon">12</string>
    <int name="key_meler" value="-9460541" />
    <string name="pp0">10</string>
    <int name="emojipopup_body_GC" value="-5534608" />
    <boolean name="abu_saleh_forward_tovoice" value="false" />
    <boolean name="key_msnewbottom_Gactive" value="true" />
    <string name="detik3">0</string>
    <string name="detik1">0</string>
    <string name="ui_home_styleV3">bywa4</string>
    <boolean name="key_msnewstabSB_check" value="true" />
    <int name="quoted_bg_picker_GCDir" value="0" />
    <int name="ModHomeMentionIconColor" value="-1305" />
    <int name="key_ms_bordabAA" value="-16049117" />
    <int name="key_msnewsbanner4" value="1" />
    <int name="key_msnewsbanner1" value="-16049117" />
    <int name="key_updown_bgcolor_GOrient" value="0" />
    <int name="key_msnewsbanner2" value="28" />
    <boolean name="bubble_more_options_dlg" value="false" />
    <int name="mas_lingkaran_kontak2" value="-12969962" />
    <boolean name="MSwa_Newb" value="true" />
    <int name="mas_lingkaran_kontak3" value="-4749920" />
    <int name="ModConBackColor" value="-662856" />
    <boolean name="hide_action_mas" value="true" />
    <boolean name="key_msnewscar_check" value="false" />
    <boolean name="Hide_contact_picker_section_recent_chats" value="false" />
    <int name="key_msnewstcabe_GC" value="-9460541" />
    <int name="key_counter_tx" value="-1" />
    <int name="HomeCounterText" value="-1" />
    <boolean name="key_mas_setBackground_quick_check" value="true" />
    <boolean name="direkt_link_degistir" value="false" />
    <boolean name="key_msnewstcabe_check" value="true" />
    <string name="pps">11</string>
    <boolean name="key_hide_wallpaper_convo_view" value="false" />
    <int name="BGColor" value="0" />
    <boolean name="key_mnt" value="true" />
    <boolean name="enable_statuspage_extras" value="true" />
    <boolean name="key_carousel_view" value="true" />
    <boolean name="key_msnewstab_check" value="true" />
    <int name="statusright" value="0" />
    <boolean name="pagetitle_picker_Gactive" value="false" />
    <boolean name="abu_saleh_play_voice_note" value="false" />
    <boolean name="quoted_divider_picker_Gactive" value="false" />
    <boolean name="multiChats" value="false" />
    <int name="ModChatEmojiColor" value="-2470337" />
    <boolean name="ModChaSendColor_Gactive" value="false" />
    <int name="ModChaSendColor" value="-1" />
    <int name="pagetitle_sel_picker" value="-662856" />
    <int name="key_ms_name" value="-463143" />
    <boolean name="onlineDotchatColor_Gactive" value="false" />
    <boolean name="key_newbordams_Gactive" value="false" />
    <int name="key_msnewbottom_GC" value="-12969962" />
    <boolean name="key_meler_Gactive" value="false" />
    <int name="tabadgeBKColor" value="-2470337" />
    <boolean name="key_msnewstntabtela_Gactive" value="true" />
    <boolean name="emojipopup_header_Gactive" value="false" />
    <boolean name="home_imgBK" value="true" />
    <boolean name="quoted_name_picker_Gactive" value="false" />
    <int name="key_ms_Ban" value="-1305" />
    <boolean name="key_msnewstabS_Gactive" value="false" />
    <boolean name="custom_wall_profilepic" value="false" />
    <boolean name="blurhader" value="true" />
    <int name="key_mas_setBackground_quick_GC" value="-1324645" />
    <int name="key_msnewschat4" value="0" />
    <boolean name="nameconfig_N" value="true" />
    <boolean name="stkr_wantsendconfirmation" value="true" />
    <int name="key_msnewschat2" value="25" />
    <int name="key_msnewschat1" value="0" />
    <int name="key_msnewstab_bl_HC" value="0" />
    <int name="tabadgeTextColor" value="-1" />
    <string name="ConvoEntry">7</string>
    <int name="ModConColor" value="-16777216" />
    <int name="key_msnewstabS2B" value="34" />
    <string name="status_reaction">💚</string>
    <int name="key_msnewscar_GC" value="-7683608" />
    <string name="tick_style">atr04</string>
    <int name="key_msnewschat_GC" value="-1324645" />
    <int name="key_msnewbottom_GOrient" value="0" />
    <boolean name="key_hide_scrollup" value="false" />
    <boolean name="ModDarkConPickColor_check" value="true" />
    <int name="tabindicator" value="-16777216" />
    <int name="quickBK_GOrient" value="0" />
    <boolean name="imsHideMStatus" value="false" />
    <boolean name="ModChatTextColor_Gactive" value="false" />
    <int name="bYW_Waa_COR_home" value="-1324645" />
    <boolean name="key_quick_view" value="true" />
    <int name="key_msnewstabS1B" value="-2470337" />
    <int name="mas_latarkontak2" value="-2470337" />
    <boolean name="key_msnewstab_custom_corners_B" value="false" />
    <boolean name="key_msnewstab_custom_corners_C" value="false" />
    <string name="key_dnd_icon">14</string>
    <int name="key_msnewstab_br_C" value="50" />
    <boolean name="blurtab" value="true" />
    <int name="key_msnewstab_bl_HX" value="50" />
    <boolean name="PicHead" value="false" />
    <boolean name="key_msnewstab_custom_corners_H" value="false" />
    <boolean name="key_botPPF" value="true" />
    <boolean name="ModFabPressedColor_Gactive" value="false" />
    <string name="inconvo_trans_option">in-y</string>
    <boolean name="key_newphoto" value="true" />
    <boolean name="ModConPickColor_Gactive" value="false" />
    <string name="HomeEntry">ms3_large</string>
    <string name="hazar_bozkurt_sesler_gelenmesaj">0</string>
    <int name="date_divider_color_picker" value="-463143" />
    <int name="key_msnewstab_tl_C" value="50" />
    <int name="main_text" value="14" />
    <boolean name="ModChatRightBubble_Gactive" value="false" />
    <boolean name="key_msnewstntabtela_check" value="true" />
    <boolean name="ModConColor_Gactive" value="false" />
    <int name="key_name_stories" value="-662856" />
    <int name="ModChatBubbleText" value="-463143" />
    <int name="rvkdmsg_icon_color" value="-2470337" />
    <boolean name="key_jamR" value="true" />
    <boolean name="ModDarkConPickColorNav_check" value="true" />
    <boolean name="ModChatGStatusB_Gactive" value="false" />
    <int name="emojipopup_icons" value="-2470337" />
    <boolean name="mswa_LxB_hM_WXW_Gactive" value="false" />
    <int name="ModContactNameColor" value="-906632520" />
    <boolean name="Audio_sensor" value="true" />
    <string name="menitnew">0</string>
    <boolean name="MasOption" value="false" />
    <int name="key_msnewstab" value="16777215" />
    <boolean name="tabadgeTextColor_Gactive" value="false" />
    <int name="key_newbordams" value="-2470337" />
    <boolean name="BGColor_Gactive" value="false" />
    <int name="key_mas_setText_contact_name" value="-662856" />
    <boolean name="key_ms_storie2" value="true" />
    <boolean name="key_ms_storie1" value="false" />
    <int name="emojipopup_body" value="-12969962" />
    <boolean name="ModChatEmojiColor_Gactive" value="false" />
    <boolean name="ModChatBtnColor_Gactive" value="false" />
    <boolean name="key_msnewstcabe_Gactive" value="false" />
    <boolean name="key_msnewstntabname_check" value="true" />
    <int name="ModChatRightBubble" value="-1160098241" />
    <boolean name="ModHomeMentionIconColor_Gactive" value="false" />
    <int name="emojipopup_header_GCDir" value="0" />
    <string name="key_search_icon">14</string>
    <int name="ModChatLeftBubble" value="-1086765481" />
    <boolean name="key_jamX" value="true" />
    <int name="jmtop" value="800" />
    <int name="key_msnewstcabe1" value="-36530" />
    <int name="quoted_bg_picker_GC" value="-12969962" />
    <boolean name="yo_want_airplanemode" value="true" />
    <int name="key_msnewstcabe2" value="27" />
    <boolean name="yo_multi_account_menu" value="true" />
    <boolean name="bYW_HMM_WWe_home" value="true" />
    <int name="key_msnewstcabe4" value="0" />
    <string name="key_menu_icon">7</string>
    <string name="papan">0</string>
    <boolean name="ModOnlineColor_Gactive" value="false" />
    <boolean name="PicProf" value="false" />
    <string name="tabb">18</string>
    <int name="key_msnewscar" value="0" />
    <boolean name="key_storiesB_Gactive" value="false" />
    <boolean name="key_msnewschat_Gactive" value="false" />
    <boolean name="key_msnewstab_Gactive" value="true" />
    <boolean name="key_msbb003" value="true" />
    <boolean name="key_updown_iconcolor_check" value="true" />
    <string name="key_custom_icondown">10</string>
    <boolean name="ModChatColor_Gactive" value="false" />
    <string name="bubble_style">atrb46</string>
    <boolean name="Ms_barraH" value="false" />
    <int name="key_msnewstcabeH" value="-12969962" />
    <boolean name="HomeCounterText_Gactive" value="false" />
    <int name="key_msnewstabS4B" value="1" />
    <string name="papannew">0</string>
    <int name="date_left_color" value="-463143" />
    <string name="key_chats_listanimation">11</string>
    <boolean name="key_digitR" value="true" />
    <boolean name="abu9aleh_status_audio" value="false" />
    <int name="quoted_name_picker" value="-463143" />
    <boolean name="key_grt2" value="true" />
    <boolean name="key_msnewbottom_check" value="true" />
    <boolean name="key_grt3" value="true" />
    <boolean name="key_grt4" value="true" />
    <int name="key_msnewstcabe_GOrient" value="4" />
    <int name="key_msnewstabSB" value="-16777216" />
    <boolean name="key_msnewstab_custom_corners_icon" value="false" />
    <boolean name="key_msnewstntab_check" value="true" />
    <int name="key_msnewstntab_GC" value="-1324645" />
    <boolean name="log_show_name_check" value="true" />
    <boolean name="tabindicator_Gactive" value="false" />
    <int name="key_msnewstntabconfig4" value="1" />
    <int name="key_msnewstabS4" value="1" />
    <boolean name="home_stories_key" value="true" />
    <int name="key_msnewstabS2" value="34" />
    <int name="key_msnewstabS1" value="-16777216" />
    <boolean name="key_header" value="true" />
    <boolean name="Hide_contact_picker_section_other_contacts" value="false" />
    <int name="fab_rounded_key" value="36" />
    <string name="menit">0</string>
    <int name="ModConPickColor" value="0" />
    <boolean name="mstela1" value="true" />
    <int name="key_dwh_size_status" value="55" />
    <string name="key_camera_icon">14</string>
    <int name="Dhourleft" value="2" />
    <string name="key_daynight_icon">4</string>
    <int name="key_msnewstntabconfig2" value="40" />
    <int name="wa_txt_color" value="-463143" />
    <int name="key_msnewstntabconfig1" value="-2470337" />
    <boolean name="date_left_color_Gactive" value="false" />
    <boolean name="rvkdmsg_icon_color_Gactive" value="false" />
    <int name="key_msnewstntabconfig_GC" value="-1324645" />
    <int name="ModConColor_GCDir" value="0" />
    <int name="key_ms_name_clock4" value="-16777216" />
    <boolean name="UnSeenColor_Gactive" value="false" />
    <int name="key_ms_name_clock3" value="-16777216" />
    <boolean name="ModConBackColor_Gactive" value="true" />
    <boolean name="key_mas_setBackground_quick_Gactive" value="false" />
    <int name="key_msnewscar2" value="21" />
    <boolean name="custom_wall" value="true" />
    <boolean name="abu_saleh_hide_list" value="true" />
    <boolean name="elapsed_time" value="false" />
    <int name="btn_voice_color_chat_picker" value="-463143" />
    <string name="key_calls_icon">20</string>
    <boolean name="ModlastseenColor_Gactive" value="false" />
    <int name="onlineDotchatColor" value="-2470337" />
    <boolean name="key_msnewstntabname_Gactive" value="false" />
    <int name="ModHomeMentionIndBackground" value="-2470337" />
    <int name="key_storiesB" value="603979776" />
    <int name="key_updown_bgcolor" value="-2470337" />
    <boolean name="key_ms_fab" value="false" />
    <int name="key_msnewstcabeH2" value="36" />
    <int name="key_msnewstcabeH1" value="-36530" />
    <int name="key_msnewschat_GOrient" value="0" />
    <int name="ModChatTextColor" value="-793131" />
    <int name="key_msnewstcabeH4" value="0" />
    <boolean name="participant_name_color_picker_Gactive" value="false" />
    <int name="key_ms_name_clock2" value="-16777216" />
    <int name="key_ms_name_clock1" value="-16777216" />
    <string name="jamm1">0</string>
    <int name="key_msnewstntabtela4" value="0" />
    <int name="key_msnewstntabtela1" value="-36530" />
    <int name="pagerleft" value="7" />
    <int name="key_msnewstntabconfigS2" value="30" />
    <string name="jamm3">0</string>
    <int name="key_msnewstntabtela2" value="36" />
</map>
